{
  "routes": [
    {
      "method": "GET",
      "path": "/coaches",
      "handler": "coach.find",
      "config": {
        "policies": []
      }
    },
    {
      "method": "GET",
      "path": "/coaches/count",
      "handler": "coach.count",
      "config": {
        "policies": []
      }
    },
    {
      "method": "GET",
      "path": "/coaches/:id",
      "handler": "coach.findOne",
      "config": {
        "policies": []
      }
    },
    {
      "method": "POST",
      "path": "/coaches",
      "handler": "coach.create",
      "config": {
        "policies": []
      }
    },
    {
      "method": "PUT",
      "path": "/coaches/:id",
      "handler": "coach.update",
      "config": {
        "policies": []
      }
    },
    {
      "method": "DELETE",
      "path": "/coaches/:id",
      "handler": "coach.delete",
      "config": {
        "policies": []
      }
    }
  ]
}
